fidle/Chrono.py
fidle/Installer.py
fidle/MagicCooker.py
fidle/MagicFeedback.py
fidle/MagicReport.py
fidle/TaskManager.py
fidle/TimeSheetManager.py
fidle/TocBuilder.py
fidle/__init__.py
fidle/config.py
fidle/fid.py
fidle/scrawler.py
fidle/utils.py
fidle/css/custom.css
fidle/css/readme.css
fidle/img/ender.svg
fidle/img/header.svg
fidle/img/logo-paysage-80px.svg
fidle/img/logo-paysage.svg
fidle/mplstyles/custom.mplstyle
fidle/templates/MagicReport_default.html
fidle/templates/MagicReport_fidle.html
fidle/templates/attestation_mail.html
fidle/templates/attestation_mail.txt
fidle-2.3.2.dist-info/LICENSE
fidle-2.3.2.dist-info/METADATA
fidle-2.3.2.dist-info/WHEEL
fidle-2.3.2.dist-info/entry_points.txt
fidle-2.3.2.dist-info/top_level.txt
fidle-2.3.2.dist-info/RECORD
