Metadata-Version: 2.1
Name: fidle
Version: 2.3.2
Summary: A nice module for the Fidle training... and much more.
Home-page: https://fidle.cnrs/fr/fidle-mod
Author: JL Parouty
Classifier: Programming Language :: Python :: 3
Classifier: License :: OSI Approved :: MIT License
Classifier: Operating System :: OS Independent
License-File: LICENSE
Requires-Dist: matplotlib
Requires-Dist: numpy
Requires-Dist: pandas
Requires-Dist: ipython
Requires-Dist: scikit-learn
Requires-Dist: pyyaml
Requires-Dist: nbformat
Requires-Dist: nbconvert
Requires-Dist: requests
Requires-Dist: typing-extensions
